andrewtools/__init__.py
andrewtools/andrewtimer.py
andrewtools/progress_bar.py
andrewtools/utils/__init__.py
andrewtools/utils/validate_input.py
andrewtools-0.1.1.dist-info/LICENSE.md
andrewtools-0.1.1.dist-info/METADATA
andrewtools-0.1.1.dist-info/WHEEL
andrewtools-0.1.1.dist-info/top_level.txt
andrewtools-0.1.1.dist-info/RECORD
