Metadata-Version: 2.1
Name: andrewtools
Version: 0.1.1
Summary: An assortment of handy Python tools made by someone named Andrew
Author-email: Andrew Tracey <act.project.alpha@gmail.com>
License: MIT License        
Project-URL: Homepage, https://github.com/andrewt110216/andrewtools
Keywords: tools,andrew,personal,handy
Classifier: Programming Language :: Python
Classifier: Programming Language :: Python :: 3
Classifier: License :: OSI Approved :: MIT License
Requires-Python: >=3.8
License-File: LICENSE.md
Provides-Extra: dev
Requires-Dist: pytest ; extra == 'dev'
Requires-Dist: black ; extra == 'dev'
